Metadata-Version: 1.0
Name: gauss-bin-distribs
Version: 0.1
Summary: Gaussian and Binomial distributions
Home-page: UNKNOWN
Author: Antonella Bernobich Dean
Author-email: UNKNOWN
License: UNKNOWN
Platform: UNKNOWN
